Metadata-Version: 1.0
Name: cloudify-agent-packager
Version: 5.0.5
Summary: Creates Cloudify Agent Packages
Home-page: https://github.com/cloudify-cosmo/cloudify-agent-packager
Author: Cloudify
Author-email: cosmo-admin@cloudify.co
License: LICENSE
Platform: All
